autogram_commons/__init__.py
autogram_commons/entity_repository_base.py
autogram_commons/file_entity_repository.py
autogram_commons/filedataloader.py
autogram_commons/identifiable.py
autogram_commons-0.3.0.dist-info/WHEEL
autogram_commons-0.3.0.dist-info/METADATA
autogram_commons-0.3.0.dist-info/RECORD
